MANIFEST.in
README.md
requirements.txt
setup.py
cgc_cli.egg-info/PKG-INFO
cgc_cli.egg-info/SOURCES.txt
cgc_cli.egg-info/dependency_links.txt
cgc_cli.egg-info/entry_points.txt
cgc_cli.egg-info/requires.txt
cgc_cli.egg-info/top_level.txt
sbg_cli/__init__.py
sbg_cli/command.py
sbg_cli/config.py
sbg_cli/context.py
sbg_cli/main.py
sbg_cli/sbg_docker/__init__.py
sbg_cli/sbg_docker/error.py
sbg_cli/sbg_docker/main.py
sbg_cli/sbg_docker/auth/__init__.py
sbg_cli/sbg_docker/auth/error.py
sbg_cli/sbg_docker/auth/sbg_auth.py
sbg_cli/sbg_docker/commands/__init__.py
sbg_cli/sbg_docker/commands/appget.py
sbg_cli/sbg_docker/commands/images.py
sbg_cli/sbg_docker/commands/login.py
sbg_cli/sbg_docker/commands/push.py
sbg_cli/sbg_docker/commands/remove.py
sbg_cli/sbg_docker/commands/sh.py
sbg_cli/sbg_docker/docker_client/__init__.py
sbg_cli/sbg_docker/docker_client/client.py
sbg_cli/sbg_docker/docker_client/error.py
sbg_cli/sbg_docker/docker_client/shell.py
sbg_cli/sbg_docker/docker_client/utils.py
sbg_cli/sbg_docker/tests/__init__.py
sbg_cli/sbg_docker/tests/tests_utils.py