Metadata-Version: 1.0
Name: cgc-cli
Version: 0.1.5
Summary: UNKNOWN
Home-page: UNKNOWN
Author: UNKNOWN
Author-email: UNKNOWN
License: AGPLv3
Platform: UNKNOWN
